conlludiff/__init__.py
conlludiff/__main__.py
conlludiff/differ.py
docs/conf.py
conlludiff-0.0.5.dist-info/LICENSE
conlludiff-0.0.5.dist-info/METADATA
conlludiff-0.0.5.dist-info/WHEEL
conlludiff-0.0.5.dist-info/top_level.txt
conlludiff-0.0.5.dist-info/RECORD
