Metadata-Version: 2.1
Name: conlludiff
Version: 0.0.5
Summary: Analyze two CONLLU files
Author-email: Peter Rupnik <rupnikpeter@gmail.com>
License: Apache License
Project-URL: Homepage, https://github.com/clarinsi/conllu-diff
Keywords: conlludiff,conllu,conll
Classifier: License :: OSI Approved :: Apache Software License
Classifier: Programming Language :: Python
Classifier: Programming Language :: Python :: 3
Requires-Python: >=3.10
License-File: LICENSE
Requires-Dist: numpy
Requires-Dist: scipy
Requires-Dist: conllu
Provides-Extra: dev
Requires-Dist: black ; extra == 'dev'
Requires-Dist: bumpver ; extra == 'dev'
Requires-Dist: isort ; extra == 'dev'
Requires-Dist: pip-tools ; extra == 'dev'
Requires-Dist: pytest ; extra == 'dev'
Requires-Dist: sphinx ; extra == 'dev'
